CPY/__main__.py
CPY/_py_write.py
CPY/_run.py
CPY/eg1.py
CPY/eg2.py
CPY/eg3.py
CPY/function.py
CPY/keywords.py
CPY/model.py
CPY/moudel.py
CPY/test.py
CPY/txt_test.py
CPY/menu/__init__.py
CPY/sll/__init__.py
chinese_python-1.2.2.dist-info/LICENSE
chinese_python-1.2.2.dist-info/METADATA
chinese_python-1.2.2.dist-info/WHEEL
chinese_python-1.2.2.dist-info/top_level.txt
chinese_python-1.2.2.dist-info/RECORD
